{"licenses":[{"name":"","id":0,"url":""}],"info":{"contributor":"","date_created":"","description":"","url":"","version":"","year":""},"categories":[{"id":1,"name":"a027","supercategory":""}],"images":[{"id":1,"width":3024,"height":3024,"file_name":"a027_1.jpg","license":0,"flickr_url":"","coco_url":"","date_captured":0},{"id":2,"width":3024,"height":3024,"file_name":"a027_2.jpg","license":0,"flickr_url":"","coco_url":"","date_captured":0},{"id":3,"width":3024,"height":3024,"file_name":"a027_3.jpg","license":0,"flickr_url":"","coco_url":"","date_captured":0},{"id":4,"width":1024,"height":1024,"file_name":"a027_4.jpg","license":0,"flickr_url":"","coco_url":"","date_captured":0}],"annotations":[{"id":1,"image_id":1,"category_id":1,"segmentation":[],"area":150001.7555,"bbox":[1974.79,1179.76,423.65,354.07],"iscrowd":0,"attributes":{"occluded":false,"rotation":0.0}},{"id":2,"image_id":2,"category_id":1,"segmentation":[],"area":53997.059199999974,"bbox":[1415.01,1098.48,266.56,202.57],"iscrowd":0,"attributes":{"occluded":false,"rotation":0.0}},{"id":3,"image_id":3,"category_id":1,"segmentation":[],"area":238314.1081999999,"bbox":[996.74,810.63,541.34,440.23],"iscrowd":0,"attributes":{"occluded":false,"rotation":0.0}},{"id":4,"image_id":4,"category_id":1,"segmentation":[],"area":3974.1500000000055,"bbox":[656.31,333.21,65.15,61.0],"iscrowd":0,"attributes":{"occluded":false,"rotation":0.0}}]}